tap_openexchangerates/__init__.py
tap_openexchangerates/client.py
tap_openexchangerates/streams.py
tap_openexchangerates/tap.py
tap_openexchangerates-0.0.1.dist-info/METADATA
tap_openexchangerates-0.0.1.dist-info/WHEEL
tap_openexchangerates-0.0.1.dist-info/entry_points.txt
tap_openexchangerates-0.0.1.dist-info/RECORD
