Metadata-Version: 2.1
Name: tap-openexchangerates
Version: 0.0.1
Summary: `tap-openexchangerates` is a Singer tap for openexchangerates, built with the Meltano Singer SDK.
License: Apache 2.0
Keywords: ELT,openexchangerates
Author: James Marcogliese
Requires-Python: >=3.7.1,<3.12
Classifier: License :: Other/Proprietary License
Classifier: Programming Language :: Python :: 3
Classifier: Programming Language :: Python :: 3.8
Classifier: Programming Language :: Python :: 3.9
Classifier: Programming Language :: Python :: 3.10
Classifier: Programming Language :: Python :: 3.11
Provides-Extra: s3
Requires-Dist: fs-s3fs (>=1.1.1,<2.0.0) ; extra == "s3"
Requires-Dist: mock (>=5.0.2,<6.0.0)
Requires-Dist: requests (>=2.28.2,<3.0.0)
Requires-Dist: responses (>=0.23.1,<0.24.0)
Requires-Dist: singer-sdk (>=0.24.0,<0.25.0)
